imcsdk/__init__.py
imcsdk/imcbasetype.py
imcsdk/imcbiostables.py
imcsdk/imcconstants.py
imcsdk/imccore.py
imcsdk/imccoremeta.py
imcsdk/imccoreutils.py
imcsdk/imcdriver.py
imcsdk/imceventhandler.py
imcsdk/imcexception.py
imcsdk/imcfilter.py
imcsdk/imcfiltertype.py
imcsdk/imcgenutils.py
imcsdk/imchandle.py
imcsdk/imcmeta.py
imcsdk/imcmethod.py
imcsdk/imcmethodfactory.py
imcsdk/imcmo.py
imcsdk/imcsession.py
imcsdk/imcxmlcodec.py
imcsdk/apis/__init__.py
imcsdk/apis/utils.py
imcsdk/apis/admin/__init__.py
imcsdk/apis/admin/certificate.py
imcsdk/apis/admin/ip.py
imcsdk/apis/admin/ipmi.py
imcsdk/apis/admin/ldap.py
imcsdk/apis/admin/ntp.py
imcsdk/apis/admin/redfish.py
imcsdk/apis/admin/snmp.py
imcsdk/apis/admin/syslog.py
imcsdk/apis/admin/user.py
imcsdk/apis/server/__init__.py
imcsdk/apis/server/adaptor.py
imcsdk/apis/server/bios.py
imcsdk/apis/server/boot.py
imcsdk/apis/server/health.py
imcsdk/apis/server/inventory.py
imcsdk/apis/server/kvm.py
imcsdk/apis/server/power.py
imcsdk/apis/server/serveractions.py
imcsdk/apis/server/sol.py
imcsdk/apis/server/storage.py
imcsdk/apis/server/vmedia.py
imcsdk/apis/v2/__init__.py
imcsdk/apis/v2/utils.py
imcsdk/apis/v2/admin/__init__.py
imcsdk/apis/v2/admin/certificate.py
imcsdk/apis/v2/admin/ip.py
imcsdk/apis/v2/admin/ipmi.py
imcsdk/apis/v2/admin/ldap.py
imcsdk/apis/v2/admin/network.py
imcsdk/apis/v2/admin/ntp.py
imcsdk/apis/v2/admin/redfish.py
imcsdk/apis/v2/admin/smtp.py
imcsdk/apis/v2/admin/snmp.py
imcsdk/apis/v2/admin/ssh.py
imcsdk/apis/v2/admin/syslog.py
imcsdk/apis/v2/admin/user.py
imcsdk/apis/v2/server/__init__.py
imcsdk/apis/v2/server/adaptor.py
imcsdk/apis/v2/server/bios.py
imcsdk/apis/v2/server/boot.py
imcsdk/apis/v2/server/health.py
imcsdk/apis/v2/server/inventory.py
imcsdk/apis/v2/server/kmip.py
imcsdk/apis/v2/server/kvm.py
imcsdk/apis/v2/server/power.py
imcsdk/apis/v2/server/pxe.py
imcsdk/apis/v2/server/serveractions.py
imcsdk/apis/v2/server/sol.py
imcsdk/apis/v2/server/storage.py
imcsdk/apis/v2/server/vic.py
imcsdk_ecoen66-0.9.28.dist-info/AUTHORS.rst
imcsdk_ecoen66-0.9.28.dist-info/LICENSE
imcsdk_ecoen66-0.9.28.dist-info/METADATA
imcsdk_ecoen66-0.9.28.dist-info/WHEEL
imcsdk_ecoen66-0.9.28.dist-info/top_level.txt
imcsdk_ecoen66-0.9.28.dist-info/RECORD
