Metadata-Version: 2.1
Name: imcsdk-ecoen66
Version: 0.9.28
Summary: python SDK for Cisco UCS IMC
Home-page: https://github.com/ecoen66/imcsdk
Author-email: ecoen@yahoo.com
License: http://www.apache.org/licenses/LICENSE-2.0
Keywords: imcsdk
Platform: UNKNOWN
Classifier: Development Status :: 4 - Beta
Classifier: Intended Audience :: Developers
Classifier: License :: OSI Approved :: Apache Software License
Classifier: Natural Language :: English
Classifier: Programming Language :: Python :: 2
Classifier: Programming Language :: Python :: 2.6
Classifier: Programming Language :: Python :: 2.7
Classifier: Programming Language :: Python :: 3
Classifier: Programming Language :: Python :: 3.3
Classifier: Programming Language :: Python :: 3.4
Classifier: Programming Language :: Python :: 3.5
Classifier: Programming Language :: Python :: 3.6
Classifier: Programming Language :: Python :: 3.7
Classifier: Programming Language :: Python :: 3.11
License-File: LICENSE
License-File: AUTHORS.rst
Requires-Dist: setuptools
Requires-Dist: pyparsing
Requires-Dist: six
Provides-Extra: docs
Requires-Dist: sphinx (<1.3) ; extra == 'docs'
Requires-Dist: sphinxcontrib-napoleon ; extra == 'docs'
Requires-Dist: sphinx-rtd-theme ; extra == 'docs'
Provides-Extra: ssl
Requires-Dist: pyOpenSSL ; extra == 'ssl'
